svfl/__init__.py
svfl/svfl.py
svfl-0.1.0.dist-info/LICENSE
svfl-0.1.0.dist-info/METADATA
svfl-0.1.0.dist-info/WHEEL
svfl-0.1.0.dist-info/top_level.txt
svfl-0.1.0.dist-info/RECORD
