Metadata-Version: 2.1
Name: svfl
Version: 0.1.0
Summary: A package for computing the average marginal contribution (Shapley Value) for each client in a Federated Learning environment
Home-page: https://github.com/akassharjun/ShapleyValueFL
Author: Akassharjun Shanmugarajah
Author-email: akassharjun@gmail.com
License: MIT
Platform: UNKNOWN
Classifier: Intended Audience :: Science/Research
Classifier: Operating System :: OS Independent
Classifier: Programming Language :: Python :: 3
Classifier: Programming Language :: Python :: 3.4
Classifier: Programming Language :: Python :: 3.5
Classifier: Programming Language :: Python :: 3.6
Classifier: Programming Language :: Python :: 3.7
License-File: LICENSE
